{"v":4,"entries":{"ui-kit-uibutton--light":{"type":"story","id":"ui-kit-uibutton--light","name":"Light","title":"Ui-Kit/UiButton","importPath":"./src/components/UI/UiButton/UiButton.stories.js","tags":["story"]},"ui-kit-uibutton--dark":{"type":"story","id":"ui-kit-uibutton--dark","name":"Dark","title":"Ui-Kit/UiButton","importPath":"./src/components/UI/UiButton/UiButton.stories.js","tags":["story"]},"ui-kit-uibutton--disabled":{"type":"story","id":"ui-kit-uibutton--disabled","name":"Disabled","title":"Ui-Kit/UiButton","importPath":"./src/components/UI/UiButton/UiButton.stories.js","tags":["story"]},"ui-kit-uiinput--default":{"type":"story","id":"ui-kit-uiinput--default","name":"Default","title":"Ui-Kit/UiInput","importPath":"./src/components/UI/UiInput/UiInput.stories.js","tags":["story"]},"ui-kit-uiloading--black":{"type":"story","id":"ui-kit-uiloading--black","name":"Black","title":"Ui-Kit/UiLoading","importPath":"./src/components/UI/UiLoading/UiLoading.stories.js","tags":["story"]},"ui-kit-uiloading--white":{"type":"story","id":"ui-kit-uiloading--white","name":"White","title":"Ui-Kit/UiLoading","importPath":"./src/components/UI/UiLoading/UiLoading.stories.js","tags":["story"]},"ui-kit-uiloading--blue":{"type":"story","id":"ui-kit-uiloading--blue","name":"Blue","title":"Ui-Kit/UiLoading","importPath":"./src/components/UI/UiLoading/UiLoading.stories.js","tags":["story"]},"ui-kit-uivideo--default":{"type":"story","id":"ui-kit-uivideo--default","name":"Default","title":"Ui-Kit/UiVideo","importPath":"./src/components/UI/UiVideo/UiVideo.stories.js","tags":["story"]}}}
